Topsis_Prerit_102217030/Topsis_Prerit_102217030.py
Topsis_Prerit_102217030/__init__.py
Topsis_Prerit_102217030/main.py
Topsis_Prerit_102217030-1.0.8.dist-info/LICENSE.txt
Topsis_Prerit_102217030-1.0.8.dist-info/METADATA
Topsis_Prerit_102217030-1.0.8.dist-info/WHEEL
Topsis_Prerit_102217030-1.0.8.dist-info/entry_points.txt
Topsis_Prerit_102217030-1.0.8.dist-info/top_level.txt
Topsis_Prerit_102217030-1.0.8.dist-info/RECORD
