Metadata-Version: 2.2
Name: Topsis_Prerit_102217030
Version: 1.0.8
Summary: A Python package for performing TOPSIS (Technique for Order of Preference by Similarity to Ideal Solution) analysis.
Author: Prerit Bhagat
Author-email: preritbhagat.pb@gmail.com
License: MIT
Project-URL: Documentation, https://github.com/Prerit-Bhagat/PYPI_Package#readme
Project-URL: Source, https://github.com/Prerit-Bhagat/PYPI_Package
Keywords: topsis mcdm multi-criteria decision-making ranking analysis
Classifier: Development Status :: 5 - Production/Stable
Classifier: Intended Audience :: Developers
Classifier: Intended Audience :: Science/Research
Classifier: Topic :: Scientific/Engineering :: Information Analysis
Classifier: License :: OSI Approved :: MIT License
Classifier: Programming Language :: Python :: 3
Classifier: Programming Language :: Python :: 3.7
Classifier: Programming Language :: Python :: 3.8
Classifier: Programming Language :: Python :: 3.9
Classifier: Programming Language :: Python :: 3.10
Requires-Python: >=3.7
License-File: LICENSE.txt
Requires-Dist: pandas>=1.0.0
Requires-Dist: numpy>=1.19.0
Dynamic: author
Dynamic: author-email
Dynamic: classifier
Dynamic: description
Dynamic: description-content-type
Dynamic: keywords
Dynamic: license
Dynamic: project-url
Dynamic: requires-dist
Dynamic: requires-python
Dynamic: summary
